saihhidrosur/__init__.py
saih_hidrosur-0.2.1.dist-info/LICENSE
saih_hidrosur-0.2.1.dist-info/METADATA
saih_hidrosur-0.2.1.dist-info/WHEEL
saih_hidrosur-0.2.1.dist-info/top_level.txt
saih_hidrosur-0.2.1.dist-info/RECORD
