Metadata-Version: 2.1
Name: saih-hidrosur
Version: 0.2.1
Summary: Library around SAIH Hidrosur data
Home-page: https://www.github.com/Frankkkkk/python-saih-hidrosur
Author: Frank Villaro-Dixon
Author-email: frank@villaro-dixon.eu
License: MIT License
Keywords: hydrology saih hidrosur
License-File: LICENSE
Requires-Dist: requests
